{
  "sections": [
    {
      "type": "responsive-banner",
      "img": "/img/uploads/categoria-leve-4-pague-3-02-100.webp",
      "link": "/vestuario"
    },
    {
      "type": "breadcrumbs",
      "enabled": true
    },
    {
      "type": "page-title"
    },
    {
      "type": "document-banner",
      "enabled": true
    },
    {
      "type": "category-retail",
      "enabled": true,
      "sort": "sales"
    },
    {
      "type": "document-description",
      "enabled": true
    }
  ]
}
